qupulse_hdawg/__about__.py
qupulse_hdawg/__init__.py
qupulse_hdawg/seqc.py
qupulse_hdawg/zihdawg.py
qupulse_hdawg-0.0.2.dist-info/METADATA
qupulse_hdawg-0.0.2.dist-info/WHEEL
qupulse_hdawg-0.0.2.dist-info/licenses/LICENSE.txt
qupulse_hdawg-0.0.2.dist-info/RECORD
