Metadata-Version: 2.1
Name: qupulse-hdawg
Version: 0.0.2
Summary: Command table based HDAWG driver for qupulse
Project-URL: Documentation, https://github.com/qutech/qupulse-hdawg#readme
Project-URL: Issues, https://github.com/qutech/qupulse-hdawg/issues
Project-URL: Source, https://github.com/qutech/qupulse-hdawg
Author-email: Simon Humpohl <simon.humpohl@rwth-aachen.de>, Max Oberländer <max.oberlaender@rwth-aachen.de>
License-Expression: GPL-3.0
License-File: LICENSE.txt
Classifier: Development Status :: 4 - Beta
Classifier: Programming Language :: Python
Classifier: Programming Language :: Python :: 3.9
Classifier: Programming Language :: Python :: 3.10
Classifier: Programming Language :: Python :: 3.11
Classifier: Programming Language :: Python :: 3.12
Classifier: Programming Language :: Python :: Implementation :: CPython
Classifier: Programming Language :: Python :: Implementation :: PyPy
Requires-Python: >=3.9
Requires-Dist: numpy
Requires-Dist: qupulse>=0.9
Requires-Dist: zhinst>=21.2.13366
